ttsdb_f5_tts/__init__.py
ttsdb_f5_tts/config.yaml
ttsdb_f5_tts/_vendor/source/.gitignore
ttsdb_f5_tts/_vendor/source/.gitmodules
ttsdb_f5_tts/_vendor/source/.pre-commit-config.yaml
ttsdb_f5_tts/_vendor/source/Dockerfile
ttsdb_f5_tts/_vendor/source/LICENSE
ttsdb_f5_tts/_vendor/source/README.md
ttsdb_f5_tts/_vendor/source/pyproject.toml
ttsdb_f5_tts/_vendor/source/ruff.toml
ttsdb_f5_tts/_vendor/source/.github/workflows/pre-commit.yaml
ttsdb_f5_tts/_vendor/source/.github/workflows/publish-docker-image.yaml
ttsdb_f5_tts/_vendor/source/.github/workflows/sync-hf.yaml
ttsdb_f5_tts/_vendor/source/ckpts/README.md
ttsdb_f5_tts/_vendor/source/data/librispeech_pc_test_clean_cross_sentence.lst
ttsdb_f5_tts/_vendor/source/data/Emilia_ZH_EN_pinyin/vocab.txt
ttsdb_f5_tts/_vendor/source/src/f5_tts/api.py
ttsdb_f5_tts/_vendor/source/src/f5_tts/socket.py
ttsdb_f5_tts/_vendor/source/src/f5_tts/eval/README.md
ttsdb_f5_tts/_vendor/source/src/f5_tts/eval/ecapa_tdnn.py
ttsdb_f5_tts/_vendor/source/src/f5_tts/eval/eval_infer_batch.py
ttsdb_f5_tts/_vendor/source/src/f5_tts/eval/eval_infer_batch.sh
ttsdb_f5_tts/_vendor/source/src/f5_tts/eval/eval_librispeech_test_clean.py
ttsdb_f5_tts/_vendor/source/src/f5_tts/eval/eval_seedtts_testset.py
ttsdb_f5_tts/_vendor/source/src/f5_tts/eval/utils_eval.py
ttsdb_f5_tts/_vendor/source/src/f5_tts/infer/README.md
ttsdb_f5_tts/_vendor/source/src/f5_tts/infer/infer_cli.py
ttsdb_f5_tts/_vendor/source/src/f5_tts/infer/infer_gradio.py
ttsdb_f5_tts/_vendor/source/src/f5_tts/infer/speech_edit.py
ttsdb_f5_tts/_vendor/source/src/f5_tts/infer/utils_infer.py
ttsdb_f5_tts/_vendor/source/src/f5_tts/infer/examples/vocab.txt
ttsdb_f5_tts/_vendor/source/src/f5_tts/infer/examples/basic/basic.toml
ttsdb_f5_tts/_vendor/source/src/f5_tts/infer/examples/basic/basic_ref_en.wav
ttsdb_f5_tts/_vendor/source/src/f5_tts/infer/examples/basic/basic_ref_zh.wav
ttsdb_f5_tts/_vendor/source/src/f5_tts/infer/examples/multi/country.flac
ttsdb_f5_tts-0.1.2.dist-info/METADATA
ttsdb_f5_tts-0.1.2.dist-info/WHEEL
ttsdb_f5_tts-0.1.2.dist-info/RECORD
