Metadata-Version: 2.4
Name: ttsdb_f5_tts
Version: 0.1.2
Summary: F5-TTS model for TTSDB
Requires-Python: <=3.14,>=3.10
Requires-Dist: accelerate>=0.33.0
Requires-Dist: bitsandbytes>0.37.0
Requires-Dist: cached-path
Requires-Dist: click
Requires-Dist: datasets
Requires-Dist: einops
Requires-Dist: ema-pytorch>=0.5.2
Requires-Dist: gradio>=3.45.2
Requires-Dist: huggingface-hub
Requires-Dist: jieba
Requires-Dist: librosa
Requires-Dist: matplotlib
Requires-Dist: numba==0.63.1
Requires-Dist: numpy<=1.26.4
Requires-Dist: pydub
Requires-Dist: pypinyin
Requires-Dist: safetensors
Requires-Dist: soundfile
Requires-Dist: tomli
Requires-Dist: torch>=2.0.0
Requires-Dist: torchaudio>=2.0.0
Requires-Dist: torchdiffeq
Requires-Dist: tqdm>=4.65.0
Requires-Dist: transformers
Requires-Dist: transformers-stream-generator
Requires-Dist: ttsdb-core>=0.1.2
Requires-Dist: vocos
Requires-Dist: wandb
Requires-Dist: x-transformers>=1.31.14
Provides-Extra: dev
Requires-Dist: pytest>=7.0.0; extra == 'dev'
